sqlalchemy_schemadisplay.py
sqlalchemy_schemadisplay-1.4.dist-info/LICENSE
sqlalchemy_schemadisplay-1.4.dist-info/METADATA
sqlalchemy_schemadisplay-1.4.dist-info/WHEEL
sqlalchemy_schemadisplay-1.4.dist-info/top_level.txt
sqlalchemy_schemadisplay-1.4.dist-info/zip-safe
sqlalchemy_schemadisplay-1.4.dist-info/RECORD
