Metadata-Version: 2.1
Name: sqlalchemy_schemadisplay
Version: 1.4
Summary: Turn SQLAlchemy DB Model into a graph
Home-page: https://github.com/fschulze/sqlalchemy_schemadisplay
Author: Florian Schulze
Author-email: florian.schulze@gmx.net
License: MIT License
Classifier: Development Status :: 5 - Production/Stable
Classifier: Intended Audience :: Developers
Classifier: License :: OSI Approved :: MIT License
Classifier: Programming Language :: Python
Classifier: Programming Language :: Python :: Implementation :: CPython
Classifier: Topic :: Database :: Front-Ends
Classifier: Operating System :: OS Independent
License-File: LICENSE
Requires-Dist: setuptools
Requires-Dist: sqlalchemy <2
Requires-Dist: pydot
